{
"companyName": "DefaultCompany",
"productName": "wreck",
"productVersion": "0.1",
"dataUrl": "wreck-webgl.data.unityweb",
"wasmCodeUrl": "wreck-webgl.wasm.code.unityweb",
"wasmFrameworkUrl": "wreck-webgl.wasm.framework.unityweb",
"graphicsAPI": ["WebGL 2.0"],
"webglContextAttributes": {"preserveDrawingBuffer": false},
"splashScreenStyle": "Dark",
"backgroundColor": "#231F20",
"cacheControl": {"default": "must-revalidate"},
"developmentBuild": false,
"multithreading": false,
"unityVersion": "2019.3.13f1"
}